mast_table/__init__.py
mast_table/conftest.py
mast_table/mast_table.py
mast_table/mast_table.vue
mast_table/validate.py
mast_table/data/column_descriptions.json
mast_table/data/unique_columns_per_mission.json
mast_table/tests/__init__.py
mast_table/tests/test_mast_table.py
mast_table/tests/data/mm_jwst_M4.ecsv
mast_table-0.0.1.dist-info/licenses/LICENSE
mast_table-0.0.1.dist-info/METADATA
mast_table-0.0.1.dist-info/WHEEL
mast_table-0.0.1.dist-info/top_level.txt
mast_table-0.0.1.dist-info/RECORD
