Metadata-Version: 2.4
Name: mast-table
Version: 0.0.1
Summary: Interact with MAST data products in a table
Author: mast-table developers
License: BSD 3-Clause License
Requires-Python: >=3.11
License-File: LICENSE
Requires-Dist: astroquery
Requires-Dist: traitlets
Requires-Dist: ipypopout
Requires-Dist: ipyvuetify
Requires-Dist: ipywidgets
Provides-Extra: test
Requires-Dist: pytest; extra == "test"
Provides-Extra: docs
Requires-Dist: sphinx-astropy[confv2]>=1.9.1; extra == "docs"
Requires-Dist: sphinx_design; extra == "docs"
Dynamic: license-file
